great_circle_calculator/__conversion.py
great_circle_calculator/__error_checking.py
great_circle_calculator/__init__.py
great_circle_calculator/_constants.py
great_circle_calculator/compass.py
great_circle_calculator/great_circle_calculator.py
great_circle_calculator-1.3.1.dist-info/LICENSE
great_circle_calculator-1.3.1.dist-info/METADATA
great_circle_calculator-1.3.1.dist-info/WHEEL
great_circle_calculator-1.3.1.dist-info/top_level.txt
great_circle_calculator-1.3.1.dist-info/RECORD
