Metadata-Version: 2.1
Name: great_circle_calculator
Version: 1.3.1
Summary: A collection of functions to calculate attributes of the great circle
Home-page: https://github.com/seangrogan/great_circle_calculator
Author: Sean Grogan
Author-email: sean.grogan@gmail.com
Classifier: Programming Language :: Python :: 3
Classifier: Programming Language :: Python :: 3.6
Classifier: Programming Language :: Python :: 3.7
Classifier: Programming Language :: Python :: 3.8
Classifier: Programming Language :: Python :: 3.9
Classifier: Programming Language :: Python :: 3.10
Classifier: License :: OSI Approved :: MIT License
Classifier: Operating System :: OS Independent
Classifier: Development Status :: 4 - Beta
Classifier: Topic :: Scientific/Engineering :: GIS
Classifier: Topic :: Utilities
License-File: LICENSE
